{
  "cta": "Close More Off-Market Deals",
  "buttonCta": "Install Workflow",
  "tagline": "Never Let a Hot Lead Go Cold.",
  "subtitle": "The ultimate workflow to convert more motivated seller leads into profitable, off-market deals.",
  "whatsInItForMe": "By instantly and persistently following up with every lead, this workflow ensures you engage hot prospects at the perfect moment, maximizing your conversions.",
  "target_audience": "Deal-focused investors who want to maximize the ROI from their lead lists.",
  "pain_point": "Hot leads are lost every day due to slow response times and inconsistent follow-up, costing you profitable deals.",
  "solution": "This workflow automates instant and persistent follow-up, ensuring every valuable lead is nurtured until they are ready to talk.",
  "highlights": [
    "Increase lead conversion rates",
    "Engage leads instantly",
    "Maximize your deal pipeline"
  ]
}